odoo/addons/sale_stock_warehouse_partner/README.rst
odoo/addons/sale_stock_warehouse_partner/__init__.py
odoo/addons/sale_stock_warehouse_partner/__manifest__.py
odoo/addons/sale_stock_warehouse_partner/i18n/sale_stock_warehouse_partner.pot
odoo/addons/sale_stock_warehouse_partner/models/__init__.py
odoo/addons/sale_stock_warehouse_partner/models/res_partner.py
odoo/addons/sale_stock_warehouse_partner/models/sale_order.py
odoo/addons/sale_stock_warehouse_partner/readme/CONTRIBUTORS.rst
odoo/addons/sale_stock_warehouse_partner/readme/DESCRIPTION.rst
odoo/addons/sale_stock_warehouse_partner/readme/USAGE.rst
odoo/addons/sale_stock_warehouse_partner/static/description/icon.png
odoo/addons/sale_stock_warehouse_partner/static/description/index.html
odoo/addons/sale_stock_warehouse_partner/tests/__init__.py
odoo/addons/sale_stock_warehouse_partner/tests/test_sale_stock_warehouse_partner.py
odoo/addons/sale_stock_warehouse_partner/views/res_partner_views.xml
odoo_addon_sale_stock_warehouse_partner-15.0.1.0.0.2.dist-info/METADATA
odoo_addon_sale_stock_warehouse_partner-15.0.1.0.0.2.dist-info/WHEEL
odoo_addon_sale_stock_warehouse_partner-15.0.1.0.0.2.dist-info/top_level.txt
odoo_addon_sale_stock_warehouse_partner-15.0.1.0.0.2.dist-info/RECORD
