Metadata-Version: 2.1
Name: odoo-addon-sale_stock_warehouse_partner
Version: 15.0.1.0.0.2
Summary: Allows to set a warehouse to a partner
Home-page: https://github.com/OCA/sale-workflow
Author: Tecnativa, Odoo Community Association (OCA), Odoo SA
Author-email: support@odoo-community.org
License: AGPL-3
Classifier: Programming Language :: Python
Classifier: Framework :: Odoo
Classifier: Framework :: Odoo :: 15.0
Classifier: License :: OSI Approved :: GNU Affero General Public License v3
Classifier: Development Status :: 3 - Alpha
Requires-Python: >=3.8
Requires-Dist: odoo<15.1dev,>=15.0a
